shortlink_extractor/__init__.py
shortlink_extractor/main.py
shortlink_extractor-1.0.0.dist-info/LICENSE
shortlink_extractor-1.0.0.dist-info/METADATA
shortlink_extractor-1.0.0.dist-info/WHEEL
shortlink_extractor-1.0.0.dist-info/top_level.txt
shortlink_extractor-1.0.0.dist-info/RECORD
